main_gas_pipeline/__init__.py
main_gas_pipeline/constants.py
main_gas_pipeline/gas_components.py
main_gas_pipeline/main_gas_pipeline.py
main_gas_pipeline/natural_gases.py
main_gas_pipeline/formulas/__init__.py
main_gas_pipeline/formulas/natural_gas.py
main_gas_pipeline/formulas/pipeline.py
main_gas_pipeline-0.0.2.dist-info/LICENSE
main_gas_pipeline-0.0.2.dist-info/METADATA
main_gas_pipeline-0.0.2.dist-info/WHEEL
main_gas_pipeline-0.0.2.dist-info/top_level.txt
main_gas_pipeline-0.0.2.dist-info/RECORD
