Metadata-Version: 2.1
Name: main-gas-pipeline
Version: 0.0.2
Summary: Main gas pipeline calculator
Home-page: UNKNOWN
Author: Buzovskyi Vitaliiy
Author-email: buzovskiy.v@gmail.com
License: UNKNOWN
Project-URL: Project on GitHub, https://github.com/Buzovskiy/main-gas-pipeline/releases/tag/v0.0.2
Project-URL: Documentation, https://main-gas-pipeline.readthedocs.io/en/v0.0.2
Project-URL: Examples, https://github.com/Buzovskiy/main-gas-pipeline/tree/master/examples
Platform: UNKNOWN
Classifier: Programming Language :: Python :: 3
Classifier: License :: OSI Approved :: MIT License
Classifier: Operating System :: OS Independent
Requires-Python: >=3.8
License-File: LICENSE
